flake8_match.py
flake8_match-1.1.0.dist-info/LICENSE
flake8_match-1.1.0.dist-info/METADATA
flake8_match-1.1.0.dist-info/WHEEL
flake8_match-1.1.0.dist-info/entry_points.txt
flake8_match-1.1.0.dist-info/top_level.txt
flake8_match-1.1.0.dist-info/RECORD
