Metadata-Version: 2.1
Name: flake8-match
Version: 1.1.0
Summary: flake8 plugin which forbids match statements (PEP 634)
Home-page: https://github.com/asottile/flake8-match
Author: Anthony Sottile
Author-email: asottile@umich.edu
License: MIT
Platform: UNKNOWN
Classifier: License :: OSI Approved :: MIT License
Classifier: Programming Language :: Python :: 3
Classifier: Programming Language :: Python :: 3 :: Only
Classifier: Programming Language :: Python :: 3.10
Classifier: Programming Language :: Python :: Implementation :: CPython
Requires-Python: >=3.10
License-File: LICENSE
Requires-Dist: flake8 (>=5.0)
